{"chapter": 44, "type": "color", "pageCount": 24, "pages": [{"n": 1, "w": 1080, "h": 721}, {"n": 2, "w": 1080, "h": 1816}, {"n": 3, "w": 1080, "h": 1807}, {"n": 4, "w": 1080, "h": 1769}, {"n": 5, "w": 1080, "h": 1800}, {"n": 6, "w": 1080, "h": 1748}, {"n": 7, "w": 1080, "h": 1816}, {"n": 8, "w": 1080, "h": 1779}, {"n": 9, "w": 1080, "h": 1807}, {"n": 10, "w": 1080, "h": 830}, {"n": 11, "w": 1080, "h": 1847}, {"n": 12, "w": 1080, "h": 1769}, {"n": 13, "w": 1080, "h": 824}, {"n": 14, "w": 1080, "h": 1794}, {"n": 15, "w": 1080, "h": 1811}, {"n": 16, "w": 1080, "h": 1786}, {"n": 17, "w": 1080, "h": 1831}, {"n": 18, "w": 1080, "h": 1820}, {"n": 19, "w": 1080, "h": 1813}, {"n": 20, "w": 1080, "h": 1732}, {"n": 21, "w": 1080, "h": 1811}, {"n": 22, "w": 1080, "h": 1759}, {"n": 23, "w": 1080, "h": 1838}, {"n": 24, "w": 1080, "h": 958}]}