{"chapter": 57, "type": "color", "pageCount": 22, "pages": [{"n": 1, "w": 1080, "h": 721}, {"n": 2, "w": 1080, "h": 1509}, {"n": 3, "w": 1080, "h": 1875}, {"n": 4, "w": 1080, "h": 1854}, {"n": 5, "w": 1080, "h": 1881}, {"n": 6, "w": 1080, "h": 1866}, {"n": 7, "w": 1080, "h": 1868}, {"n": 8, "w": 1080, "h": 1883}, {"n": 9, "w": 1080, "h": 1870}, {"n": 10, "w": 1080, "h": 1868}, {"n": 11, "w": 1080, "h": 1856}, {"n": 12, "w": 1080, "h": 1854}, {"n": 13, "w": 1080, "h": 1871}, {"n": 14, "w": 1080, "h": 1864}, {"n": 15, "w": 1080, "h": 1881}, {"n": 16, "w": 1080, "h": 1860}, {"n": 17, "w": 1080, "h": 1870}, {"n": 18, "w": 1080, "h": 1887}, {"n": 19, "w": 1080, "h": 1864}, {"n": 20, "w": 1080, "h": 1850}, {"n": 21, "w": 1080, "h": 1860}, {"n": 22, "w": 1080, "h": 958}]}